{"active_chip":null,"automatic_subs":[{"entry":9378299,"element_in":335,"element_out":226,"event":34},{"entry":9378299,"element_in":261,"element_out":72,"event":34}],"entry_history":{"event":34,"points":28,"total_points":1567,"rank":8645337,"rank_sort":8850775,"overall_rank":8245772,"percentile_rank":70,"bank":1,"value":980,"event_transfers":0,"event_transfers_cost":0,"points_on_bench":0},"picks":[{"element":1,"position":1,"multiplier":1,"is_captain":false,"is_vice_captain":false,"element_type":1},{"element":476,"position":2,"multiplier":1,"is_captain":false,"is_vice_captain":false,"element_type":2},{"element":5,"position":3,"multiplier":1,"is_captain":false,"is_vice_captain":false,"element_type":2},{"element":261,"position":4,"multiplier":1,"is_captain":false,"is_vice_captain":false,"element_type":2},{"element":335,"position":5,"multiplier":1,"is_captain":false,"is_vice_captain":false,"element_type":3},{"element":16,"position":6,"multiplier":2,"is_captain":false,"is_vice_captain":true,"element_type":3},{"element":582,"position":7,"multiplier":1,"is_captain":false,"is_vice_captain":false,"element_type":3},{"element":299,"position":8,"multiplier":1,"is_captain":false,"is_vice_captain":false,"element_type":3},{"element":82,"position":9,"multiplier":1,"is_captain":false,"is_vice_captain":false,"element_type":3},{"element":430,"position":10,"multiplier":1,"is_captain":true,"is_vice_captain":false,"element_type":4},{"element":714,"position":11,"multiplier":1,"is_captain":false,"is_vice_captain":false,"element_type":4},{"element":470,"position":12,"multiplier":0,"is_captain":false,"is_vice_captain":false,"element_type":1},{"element":100,"position":13,"multiplier":0,"is_captain":false,"is_vice_captain":false,"element_type":4},{"element":226,"position":14,"multiplier":0,"is_captain":false,"is_vice_captain":false,"element_type":2},{"element":72,"position":15,"multiplier":0,"is_captain":false,"is_vice_captain":false,"element_type":2}]}